<?xml version="1.0" encoding="UTF-8"?>

<!-- generated on 2026-04-12 21:03:04.082623 by Eclipse SUMO osmwebwizard.py v1_26_0+0000-fa7df22d7f1
<configuration>
    <net-file value="C:\Program Files (x86)\Eclipse\Sumo\2026-04-12-21-02-35\osm.net.xml.gz"/>
    <output-trip-file value="C:\Program Files (x86)\Eclipse\Sumo\2026-04-12-21-02-35\osm.passenger.trips.xml"/>
    <route-file value="C:\Program Files (x86)\Eclipse\Sumo\2026-04-12-21-02-35\osm.passenger.rou.xml"/>
    <prefix value="veh"/>
    <trip-attributes value="departLane=&quot;best&quot;"/>
    <fringe-start-attributes value="departSpeed=&quot;max&quot;"/>
    <vehicle-class value="passenger"/>
    <lanes value="True"/>
    <fringe-factor value="15"/>
    <allow-fringe.min-length value="1000.0"/>
    <edge-permission value="passenger"/>
    <via-edge-types value="highway.motorway,highway.motorway_link,highway.trunk_link,highway.primary_link,highway.secondary_link,highway.tertiary_link"/>
    <seed value="45"/>
    <min-distance value="300.0"/>
    <min-distance.fringe value="10.0"/>
    <remove-loops value="True"/>
    <end value="600.0"/>
    <insertion-density value="40.0"/>
</configuration>
-->

<routes xmlns:xsi="http://www.w3.org/2001/XMLSchema-instance" xsi:noNamespaceSchemaLocation="http://sumo.dlr.de/xsd/routes_file.xsd">
    <vType id="veh_passenger" vClass="passenger"/>
    <trip id="veh0" depart="0.00" from="-424514808" to="115561673#4" departLane="best" type="veh_passenger" departSpeed="max"/>
    <trip id="veh1" depart="1.13" from="-115673859#1" to="1057883200#1" departLane="best" type="veh_passenger" departSpeed="max"/>
    <trip id="veh2" depart="2.25" from="-115561673#3" to="-103426225#5" departLane="best" type="veh_passenger"/>
    <trip id="veh3" depart="3.38" from="-624091858#3" to="243006968#1" departLane="best" type="veh_passenger" departSpeed="max"/>
    <trip id="veh4" depart="4.50" from="-1125937900#1" to="1491172359#0" departLane="best" type="veh_passenger"/>
    <trip id="veh5" depart="5.63" from="-1461641387" to="38393868#0" departLane="best" type="veh_passenger" departSpeed="max"/>
    <trip id="veh6" depart="6.75" from="184745185#5" to="-38359857#0" departLane="best" type="veh_passenger"/>
    <trip id="veh7" depart="7.88" from="38359857#0" to="203589962#1" departLane="best" type="veh_passenger" departSpeed="max"/>
    <trip id="veh8" depart="9.00" from="-115561673#4" to="114531734#2" departLane="best" type="veh_passenger" departSpeed="max"/>
    <trip id="veh9" depart="10.13" from="1491183963" to="683745965#0" departLane="best" type="veh_passenger" departSpeed="max"/>
    <trip id="veh10" depart="11.25" from="-1491172372#1" to="-547154355#0" departLane="best" type="veh_passenger"/>
    <trip id="veh11" depart="12.38" from="203589969#1" to="87494508#0" departLane="best" type="veh_passenger"/>
    <trip id="veh12" depart="13.50" from="1013138963#0" to="547154356#1" departLane="best" type="veh_passenger" departSpeed="max"/>
    <trip id="veh13" depart="14.63" from="38393875#1" to="203589977#1" departLane="best" type="veh_passenger"/>
    <trip id="veh14" depart="15.75" from="266143650#2" to="1491183946#2" departLane="best" type="veh_passenger"/>
    <trip id="veh15" depart="16.88" from="1420160202" to="-114532723#0" departLane="best" type="veh_passenger"/>
    <trip id="veh16" depart="18.00" from="547154357#0" to="630462798#5" departLane="best" type="veh_passenger"/>
    <trip id="veh17" depart="19.13" from="-875027029#2" to="1491172360#0" departLane="best" type="veh_passenger"/>
    <trip id="veh18" depart="20.25" from="1461641434#1" to="-911225805#1" departLane="best" type="veh_passenger"/>
    <trip id="veh19" depart="21.38" from="108045029#0" to="422195693#1" departLane="best" type="veh_passenger" departSpeed="max"/>
    <trip id="veh20" depart="22.50" from="-1461641442#1" to="115560947#0" departLane="best" type="veh_passenger" departSpeed="max"/>
    <trip id="veh21" depart="23.63" from="38691414#1" to="148331423" departLane="best" type="veh_passenger"/>
    <trip id="veh22" depart="24.75" from="-108934130" to="453743055" departLane="best" type="veh_passenger"/>
    <trip id="veh23" depart="25.88" from="-459456563" to="-911225805#1" departLane="best" type="veh_passenger"/>
    <trip id="veh24" depart="27.00" from="-203589956#1" to="148331423" departLane="best" type="veh_passenger" departSpeed="max"/>
    <trip id="veh25" depart="28.13" from="-115514116#5" to="723313369#4" departLane="best" type="veh_passenger" departSpeed="max"/>
    <trip id="veh26" depart="29.25" from="-115684382" to="1491172358" departLane="best" type="veh_passenger" departSpeed="max"/>
    <trip id="veh27" depart="30.38" from="-424514814#1" to="115560895#1" departLane="best" type="veh_passenger" departSpeed="max"/>
    <trip id="veh28" depart="31.51" from="-646265607#0" to="875027029#2" departLane="best" type="veh_passenger"/>
    <trip id="veh29" depart="32.63" from="1461641443#0" to="116451461#1" departLane="best" type="veh_passenger" departSpeed="max"/>
    <trip id="veh30" depart="33.76" from="1491172357#1" to="115673859#1" departLane="best" type="veh_passenger"/>
    <trip id="veh31" depart="34.88" from="-1461641452#0" to="-108045029#0" departLane="best" type="veh_passenger"/>
    <trip id="veh32" depart="36.01" from="203589976#3" to="547154357#3" departLane="best" type="veh_passenger"/>
    <trip id="veh33" depart="37.13" from="-115561180#2" to="-1461641433#1" departLane="best" type="veh_passenger"/>
    <trip id="veh34" depart="38.26" from="1013138963#0" to="1462125975" departLane="best" type="veh_passenger" departSpeed="max"/>
    <trip id="veh35" depart="39.38" from="-115673859#1" to="184745185#1" departLane="best" type="veh_passenger" departSpeed="max"/>
    <trip id="veh36" depart="40.51" from="38359857#0" to="108932067" departLane="best" type="veh_passenger" departSpeed="max"/>
    <trip id="veh37" depart="41.63" from="266157747" to="108899907#1" departLane="best" type="veh_passenger" departSpeed="max"/>
    <trip id="veh38" depart="42.76" from="1062204371" to="108686053#1" departLane="best" type="veh_passenger"/>
    <trip id="veh39" depart="43.88" from="-115561673#3" to="1461641458#3" departLane="best" type="veh_passenger"/>
    <trip id="veh40" depart="45.01" from="372020013#1" to="164415954#2" departLane="best" type="veh_passenger"/>
    <trip id="veh41" depart="46.13" from="417192344#2" to="-38359857#1" departLane="best" type="veh_passenger"/>
    <trip id="veh42" depart="47.26" from="723313369#6" to="1099670074#1" departLane="best" type="veh_passenger"/>
    <trip id="veh43" depart="48.38" from="115561079" to="203589956#1" departLane="best" type="veh_passenger" departSpeed="max"/>
    <trip id="veh44" depart="49.51" from="1491183946#0" to="1461641460" departLane="best" type="veh_passenger"/>
    <trip id="veh45" depart="50.63" from="38393875#1" to="1491183944#2" departLane="best" type="veh_passenger"/>
    <trip id="veh46" depart="51.76" from="570104370" to="1491183956" departLane="best" type="veh_passenger" departSpeed="max"/>
    <trip id="veh47" depart="52.88" from="1365389583#0" to="-114532723#0" departLane="best" type="veh_passenger"/>
    <trip id="veh48" depart="54.01" from="1461641433#0" to="108045029#1" departLane="best" type="veh_passenger"/>
    <trip id="veh49" depart="55.13" from="1461641457#0" to="417228502#2" departLane="best" type="veh_passenger"/>
    <trip id="veh50" depart="56.26" from="694756702#0" to="38691386#1" departLane="best" type="veh_passenger" departSpeed="max"/>
    <trip id="veh51" depart="57.38" from="38359849#1" to="108895901#0" departLane="best" type="veh_passenger"/>
    <trip id="veh52" depart="58.51" from="-115560946#1" to="30951906#1" departLane="best" type="veh_passenger"/>
    <trip id="veh53" depart="59.63" from="949547104" to="115561161#1" departLane="best" type="veh_passenger" departSpeed="max"/>
    <trip id="veh54" depart="60.76" from="545148171#0" to="1461641387" departLane="best" type="veh_passenger"/>
    <trip id="veh55" depart="61.88" from="1013138963#0" to="422195693#1" departLane="best" type="veh_passenger" departSpeed="max"/>
    <trip id="veh56" depart="63.01" from="1491183962#1" to="-115560987" departLane="best" type="veh_passenger"/>
    <trip id="veh57" depart="64.14" from="115561669#0" to="108932067" departLane="best" type="veh_passenger" departSpeed="max"/>
    <trip id="veh58" depart="65.26" from="-266143655#4" to="114531734#2" departLane="best" type="veh_passenger"/>
    <trip id="veh59" depart="66.39" from="138652753#1" to="38359851#1" departLane="best" type="veh_passenger"/>
    <trip id="veh60" depart="67.51" from="1068837568" to="1461641442#1" departLane="best" type="veh_passenger"/>
    <trip id="veh61" depart="68.64" from="243006970#1" to="931220687#0" departLane="best" type="veh_passenger"/>
    <trip id="veh62" depart="69.76" from="154717201#0" to="875071472" departLane="best" type="veh_passenger" departSpeed="max"/>
    <trip id="veh63" depart="70.89" from="1461641459#1" to="-725287636#0" departLane="best" type="veh_passenger"/>
    <trip id="veh64" depart="72.01" from="38393869#0" to="154717203#0" departLane="best" type="veh_passenger"/>
    <trip id="veh65" depart="73.14" from="1461641439" to="-1461641443#1" departLane="best" type="veh_passenger"/>
    <trip id="veh66" depart="74.26" from="115673962#0" to="1057883200#1" departLane="best" type="veh_passenger" departSpeed="max"/>
    <trip id="veh67" depart="75.39" from="116625957#0" to="694603072" departLane="best" type="veh_passenger"/>
    <trip id="veh68" depart="76.51" from="1004744421" to="-108045029#0" departLane="best" type="veh_passenger"/>
    <trip id="veh69" depart="77.64" from="108045029#0" to="1057883200#1" departLane="best" type="veh_passenger" departSpeed="max"/>
    <trip id="veh70" depart="78.76" from="115560987" to="-694756702#0" departLane="best" type="veh_passenger" departSpeed="max"/>
    <trip id="veh71" depart="79.89" from="38393992#1" to="410552443" departLane="best" type="veh_passenger"/>
    <trip id="veh72" depart="81.01" from="459456564#4" to="-138652733" departLane="best" type="veh_passenger"/>
    <trip id="veh73" depart="82.14" from="115561082#0" to="-38691413" departLane="best" type="veh_passenger" departSpeed="max"/>
    <trip id="veh74" depart="83.26" from="1462125970" to="115560947#1" departLane="best" type="veh_passenger"/>
    <trip id="veh75" depart="84.39" from="114532723#0" to="-115561670#0" departLane="best" type="veh_passenger" departSpeed="max"/>
    <trip id="veh76" depart="85.51" from="108646023#0" to="-266143646#1" departLane="best" type="veh_passenger"/>
    <trip id="veh77" depart="86.64" from="115561079" to="466365026" departLane="best" type="veh_passenger" departSpeed="max"/>
    <trip id="veh78" depart="87.76" from="694603076#0" to="-1461641443#1" departLane="best" type="veh_passenger"/>
    <trip id="veh79" depart="88.89" from="-1423673546" to="949547103#1" departLane="best" type="veh_passenger"/>
    <trip id="veh80" depart="90.01" from="115561079" to="1491172368#0" departLane="best" type="veh_passenger" departSpeed="max"/>
    <trip id="veh81" depart="91.14" from="1491183960" to="114533140#1" departLane="best" type="veh_passenger"/>
    <trip id="veh82" depart="92.26" from="1013138963#0" to="466365026" departLane="best" type="veh_passenger" departSpeed="max"/>
    <trip id="veh83" depart="93.39" from="1461641435" to="-108045029#0" departLane="best" type="veh_passenger"/>
    <trip id="veh84" depart="94.52" from="-114531734#2" to="422195701" departLane="best" type="veh_passenger" departSpeed="max"/>
    <trip id="veh85" depart="95.64" from="1420160202" to="243007677" departLane="best" type="veh_passenger"/>
    <trip id="veh86" depart="96.77" from="115560983#2" to="203589956#1" departLane="best" type="veh_passenger"/>
    <trip id="veh87" depart="97.89" from="-824158743#2" to="1057888578" departLane="best" type="veh_passenger"/>
    <trip id="veh88" depart="99.02" from="723313366#2" to="547154356#1" departLane="best" type="veh_passenger"/>
    <trip id="veh89" depart="100.14" from="115561204#0" to="-1099670076#1" departLane="best" type="veh_passenger" departSpeed="max"/>
    <trip id="veh90" depart="101.27" from="1461641443#0" to="87494508#1" departLane="best" type="veh_passenger" departSpeed="max"/>
    <trip id="veh91" depart="102.39" from="108686154#0" to="-1491183966#0" departLane="best" type="veh_passenger" departSpeed="max"/>
    <trip id="veh92" depart="103.52" from="-1462125975" to="-115561670#0" departLane="best" type="veh_passenger" departSpeed="max"/>
    <trip id="veh93" depart="104.64" from="931398779" to="646265608" departLane="best" type="veh_passenger"/>
    <trip id="veh94" depart="105.77" from="-453743055" to="-115561669#0" departLane="best" type="veh_passenger" departSpeed="max"/>
    <trip id="veh95" depart="106.89" from="-949547103#1" to="266143650#1" departLane="best" type="veh_passenger" departSpeed="max"/>
    <trip id="veh96" depart="108.02" from="694756702#0" to="115560897" departLane="best" type="veh_passenger" departSpeed="max"/>
    <trip id="veh97" depart="109.14" from="38359857#0" to="203589954#2" departLane="best" type="veh_passenger" departSpeed="max"/>
    <trip id="veh98" depart="110.27" from="931388877" to="-1461641443#1" departLane="best" type="veh_passenger"/>
    <trip id="veh99" depart="111.39" from="694756702#0" to="-911225805#1" departLane="best" type="veh_passenger" departSpeed="max"/>
    <trip id="veh100" depart="112.52" from="-115561673#4" to="-1461641443#1" departLane="best" type="veh_passenger" departSpeed="max"/>
    <trip id="veh101" depart="113.64" from="-108899907#2" to="1309272820" departLane="best" type="veh_passenger"/>
    <trip id="veh102" depart="114.77" from="1461641443#0" to="-875027029#1" departLane="best" type="veh_passenger" departSpeed="max"/>
    <trip id="veh103" depart="115.89" from="-1087007031" to="-108882988" departLane="best" type="veh_passenger"/>
    <trip id="veh104" depart="117.02" from="1491183954#0" to="-1004737860" departLane="best" type="veh_passenger"/>
    <trip id="veh105" depart="118.14" from="1461641443#0" to="-114532723#0" departLane="best" type="veh_passenger" departSpeed="max"/>
    <trip id="veh106" depart="119.27" from="-203589956#1" to="417235700" departLane="best" type="veh_passenger" departSpeed="max"/>
    <trip id="veh107" depart="120.39" from="1137637521#1" to="115673859#1" departLane="best" type="veh_passenger"/>
    <trip id="veh108" depart="121.52" from="266157747" to="1491183956" departLane="best" type="veh_passenger" departSpeed="max"/>
    <trip id="veh109" depart="122.64" from="-1491172369#0" to="115561168#3" departLane="best" type="veh_passenger"/>
    <trip id="veh110" depart="123.77" from="723313369#4" to="-266143646#1" departLane="best" type="veh_passenger"/>
    <trip id="veh111" depart="124.90" from="1028732094#0" to="-266143646#1" departLane="best" type="veh_passenger"/>
    <trip id="veh112" depart="126.02" from="-453743055" to="-38375844#2" departLane="best" type="veh_passenger" departSpeed="max"/>
    <trip id="veh113" depart="127.15" from="1461641457#0" to="249079040#1" departLane="best" type="veh_passenger"/>
    <trip id="veh114" depart="128.27" from="38691390#3" to="-1461641443#1" departLane="best" type="veh_passenger"/>
    <trip id="veh115" depart="129.40" from="949547104" to="154717203#0" departLane="best" type="veh_passenger" departSpeed="max"/>
    <trip id="veh116" depart="130.52" from="-424514808" to="154717203#0" departLane="best" type="veh_passenger" departSpeed="max"/>
    <trip id="veh117" depart="131.65" from="-424514808" to="-115560988#2" departLane="best" type="veh_passenger" departSpeed="max"/>
    <trip id="veh118" depart="132.77" from="-249079040#2" to="453743055" departLane="best" type="veh_passenger" departSpeed="max"/>
    <trip id="veh119" depart="133.90" from="-988510417#2" to="1491183957" departLane="best" type="veh_passenger"/>
    <trip id="veh120" depart="135.02" from="1125927214#2" to="-38691413" departLane="best" type="veh_passenger"/>
    <trip id="veh121" depart="136.15" from="108882988" to="-38393869#0" departLane="best" type="veh_passenger" departSpeed="max"/>
    <trip id="veh122" depart="137.27" from="108882988" to="-266143646#1" departLane="best" type="veh_passenger" departSpeed="max"/>
    <trip id="veh123" depart="138.40" from="-1461641387" to="38393860#0" departLane="best" type="veh_passenger" departSpeed="max"/>
    <trip id="veh124" depart="139.52" from="694603072" to="646265607#0" departLane="best" type="veh_passenger"/>
    <trip id="veh125" depart="140.65" from="348587225#1" to="115673859#1" departLane="best" type="veh_passenger"/>
    <trip id="veh126" depart="141.77" from="115561078" to="-1068024437#0" departLane="best" type="veh_passenger" departSpeed="max"/>
    <trip id="veh127" depart="142.90" from="203589970#0" to="624091858#3" departLane="best" type="veh_passenger"/>
    <trip id="veh128" depart="144.02" from="115673962#0" to="-38393992#2" departLane="best" type="veh_passenger" departSpeed="max"/>
    <trip id="veh129" depart="145.15" from="38691386#1" to="1420160203" departLane="best" type="veh_passenger"/>
    <trip id="veh130" depart="146.27" from="-1491183944#0" to="1461641442#1" departLane="best" type="veh_passenger"/>
    <trip id="veh131" depart="147.40" from="38375826" to="-1461641464" departLane="best" type="veh_passenger"/>
    <trip id="veh132" depart="148.52" from="-1462125975" to="1491172369#0" departLane="best" type="veh_passenger" departSpeed="max"/>
    <trip id="veh133" depart="149.65" from="-1461641387" to="266143651#1" departLane="best" type="veh_passenger" departSpeed="max"/>
    <trip id="veh134" depart="150.77" from="1461641422#0" to="115561179#1" departLane="best" type="veh_passenger" departSpeed="max"/>
    <trip id="veh135" depart="151.90" from="113595957#0" to="875070295" departLane="best" type="veh_passenger" departSpeed="max"/>
    <trip id="veh136" depart="153.02" from="-571179089#1" to="1461641388" departLane="best" type="veh_passenger" departSpeed="max"/>
    <trip id="veh137" depart="154.15" from="108885733#0" to="824174715" departLane="best" type="veh_passenger"/>
    <trip id="veh138" depart="155.27" from="1004744421" to="-1004744417" departLane="best" type="veh_passenger"/>
    <trip id="veh139" depart="156.40" from="417228502#1" to="-459456563" departLane="best" type="veh_passenger"/>
    <trip id="veh140" depart="157.53" from="1461641443#0" to="422195693#1" departLane="best" type="veh_passenger" departSpeed="max"/>
    <trip id="veh141" depart="158.65" from="417228502#2" to="38691389#0" departLane="best" type="veh_passenger"/>
    <trip id="veh142" depart="159.78" from="1462125970" to="114533140#1" departLane="best" type="veh_passenger"/>
    <trip id="veh143" depart="160.90" from="38691413" to="87494509#5" departLane="best" type="veh_passenger" departSpeed="max"/>
    <trip id="veh144" depart="162.03" from="108045029#0" to="114150961#2" departLane="best" type="veh_passenger" departSpeed="max"/>
    <trip id="veh145" depart="163.15" from="875021163" to="-108686154#0" departLane="best" type="veh_passenger" departSpeed="max"/>
    <trip id="veh146" depart="164.28" from="723313366#1" to="417235700" departLane="best" type="veh_passenger"/>
    <trip id="veh147" depart="165.40" from="-203589956#1" to="1491172365#2" departLane="best" type="veh_passenger" departSpeed="max"/>
    <trip id="veh148" depart="166.53" from="1004744419" to="243008519#1" departLane="best" type="veh_passenger"/>
    <trip id="veh149" depart="167.65" from="570104370" to="249079040#1" departLane="best" type="veh_passenger" departSpeed="max"/>
    <trip id="veh150" depart="168.78" from="38359851#1" to="-875027029#1" departLane="best" type="veh_passenger"/>
    <trip id="veh151" depart="169.90" from="115560987" to="115561179#0" departLane="best" type="veh_passenger" departSpeed="max"/>
    <trip id="veh152" depart="171.03" from="694756702#0" to="-38359857#0" departLane="best" type="veh_passenger" departSpeed="max"/>
    <trip id="veh153" depart="172.15" from="-87494509#1" to="694609277#0" departLane="best" type="veh_passenger"/>
    <trip id="veh154" depart="173.28" from="547154355#0" to="-547266341" departLane="best" type="veh_passenger" departSpeed="max"/>
    <trip id="veh155" depart="174.40" from="-630462798#5" to="1491183944#1" departLane="best" type="veh_passenger" departSpeed="max"/>
    <trip id="veh156" depart="175.53" from="-1461641387" to="-875070294" departLane="best" type="veh_passenger" departSpeed="max"/>
    <trip id="veh157" depart="176.65" from="-135704149" to="203589956#1" departLane="best" type="veh_passenger"/>
    <trip id="veh158" depart="177.78" from="38359845#1" to="1423662169#0" departLane="best" type="veh_passenger"/>
    <trip id="veh159" depart="178.90" from="1461641462" to="-417309446#2" departLane="best" type="veh_passenger"/>
    <trip id="veh160" depart="180.03" from="1491183946#0" to="1057883200#1" departLane="best" type="veh_passenger"/>
    <trip id="veh161" depart="181.15" from="-115514116#5" to="108932696" departLane="best" type="veh_passenger" departSpeed="max"/>
    <trip id="veh162" depart="182.28" from="-1461641387" to="-1461641443#1" departLane="best" type="veh_passenger" departSpeed="max"/>
    <trip id="veh163" depart="183.40" from="185549299" to="1428233169" departLane="best" type="veh_passenger" departSpeed="max"/>
    <trip id="veh164" depart="184.53" from="1491183960" to="-1491183966#0" departLane="best" type="veh_passenger"/>
    <trip id="veh165" depart="185.65" from="1461641443#0" to="372020013#1" departLane="best" type="veh_passenger" departSpeed="max"/>
    <trip id="veh166" depart="186.78" from="114150961#1" to="1030215636" departLane="best" type="veh_passenger"/>
    <trip id="veh167" depart="187.91" from="38359857#0" to="1461641387" departLane="best" type="veh_passenger" departSpeed="max"/>
    <trip id="veh168" depart="189.03" from="114532723#0" to="108933164" departLane="best" type="veh_passenger" departSpeed="max"/>
    <trip id="veh169" depart="190.16" from="-1473695733" to="-243006970#1" departLane="best" type="veh_passenger"/>
    <trip id="veh170" depart="191.28" from="-424514808" to="-1068024437#0" departLane="best" type="veh_passenger" departSpeed="max"/>
    <trip id="veh171" depart="192.41" from="-1462125975" to="1461641452#1" departLane="best" type="veh_passenger" departSpeed="max"/>
    <trip id="veh172" depart="193.53" from="115561204#0" to="1461641442#1" departLane="best" type="veh_passenger" departSpeed="max"/>
    <trip id="veh173" depart="194.66" from="99682907#2" to="116457542#3" departLane="best" type="veh_passenger"/>
    <trip id="veh174" depart="195.78" from="203589957#1" to="-931220687#0" departLane="best" type="veh_passenger"/>
    <trip id="veh175" depart="196.91" from="266143646#0" to="1365389583#1" departLane="best" type="veh_passenger" departSpeed="max"/>
    <trip id="veh176" depart="198.03" from="38375838" to="824174714" departLane="best" type="veh_passenger"/>
    <trip id="veh177" depart="199.16" from="-203589969#0" to="547154357#3" departLane="best" type="veh_passenger"/>
    <trip id="veh178" depart="200.28" from="1461641443#0" to="547154357#3" departLane="best" type="veh_passenger" departSpeed="max"/>
    <trip id="veh179" depart="201.41" from="-115514116#5" to="422195701" departLane="best" type="veh_passenger" departSpeed="max"/>
    <trip id="veh180" depart="202.53" from="-453743055" to="1030215635" departLane="best" type="veh_passenger" departSpeed="max"/>
    <trip id="veh181" depart="203.66" from="115561204#0" to="422195693#1" departLane="best" type="veh_passenger" departSpeed="max"/>
    <trip id="veh182" depart="204.78" from="1004737861#1" to="949547103#1" departLane="best" type="veh_passenger"/>
    <trip id="veh183" depart="205.91" from="417235733#1" to="203589978#1" departLane="best" type="veh_passenger"/>
    <trip id="veh184" depart="207.03" from="38359868#1" to="-1068024437#0" departLane="best" type="veh_passenger"/>
    <trip id="veh185" depart="208.16" from="1461641434#1" to="624091858#1" departLane="best" type="veh_passenger"/>
    <trip id="veh186" depart="209.28" from="-723387976#1" to="1462125975" departLane="best" type="veh_passenger" departSpeed="max"/>
    <trip id="veh187" depart="210.41" from="-115684382" to="249079040#1" departLane="best" type="veh_passenger" departSpeed="max"/>
    <trip id="veh188" depart="211.53" from="-266143655#6" to="875149910#1" departLane="best" type="veh_passenger"/>
    <trip id="veh189" depart="212.66" from="1461641422#0" to="-1137637521#0" departLane="best" type="veh_passenger" departSpeed="max"/>
    <trip id="veh190" depart="213.78" from="115561082#0" to="-138652733" departLane="best" type="veh_passenger" departSpeed="max"/>
    <trip id="veh191" depart="214.91" from="-630462798#5" to="154717203#0" departLane="best" type="veh_passenger" departSpeed="max"/>
    <trip id="veh192" depart="216.03" from="-115673859#1" to="417309446#0" departLane="best" type="veh_passenger" departSpeed="max"/>
    <trip id="veh193" depart="217.16" from="1491183954#1" to="154717203#0" departLane="best" type="veh_passenger"/>
    <trip id="veh194" depart="218.29" from="-630462798#2" to="-115561670#1" departLane="best" type="veh_passenger"/>
    <trip id="veh195" depart="219.41" from="115561082#0" to="154717203#0" departLane="best" type="veh_passenger" departSpeed="max"/>
    <trip id="veh196" depart="220.54" from="723312334#3" to="1491183965" departLane="best" type="veh_passenger"/>
    <trip id="veh197" depart="221.66" from="-38375826" to="1409708183" departLane="best" type="veh_passenger"/>
    <trip id="veh198" depart="222.79" from="-115561168#3" to="1491172368#0" departLane="best" type="veh_passenger"/>
    <trip id="veh199" depart="223.91" from="38359895" to="115561673#4" departLane="best" type="veh_passenger"/>
    <trip id="veh200" depart="225.04" from="1491183950#1" to="-1491172357#1" departLane="best" type="veh_passenger"/>
    <trip id="veh201" depart="226.16" from="1491172369#0" to="138652733" departLane="best" type="veh_passenger"/>
    <trip id="veh202" depart="227.29" from="243006968#1" to="115673859#1" departLane="best" type="veh_passenger"/>
    <trip id="veh203" depart="228.41" from="1099670075#0" to="115560897" departLane="best" type="veh_passenger"/>
    <trip id="veh204" depart="229.54" from="417228502#2" to="949547103#1" departLane="best" type="veh_passenger"/>
    <trip id="veh205" depart="230.66" from="115561079" to="-459456564#2" departLane="best" type="veh_passenger" departSpeed="max"/>
    <trip id="veh206" depart="231.79" from="417228502#2" to="-115561669#0" departLane="best" type="veh_passenger"/>
    <trip id="veh207" depart="232.91" from="1033645485" to="630462798#5" departLane="best" type="veh_passenger"/>
    <trip id="veh208" depart="234.04" from="-1125937899#1" to="422195693#1" departLane="best" type="veh_passenger"/>
    <trip id="veh209" depart="235.16" from="-115561179#1" to="203589978#4" departLane="best" type="veh_passenger" departSpeed="max"/>
    <trip id="veh210" depart="236.29" from="723312334#5" to="-108045029#0" departLane="best" type="veh_passenger"/>
    <trip id="veh211" depart="237.41" from="-38393865" to="417235727#2" departLane="best" type="veh_passenger"/>
    <trip id="veh212" depart="238.54" from="243006567#1" to="1461641452#1" departLane="best" type="veh_passenger"/>
    <trip id="veh213" depart="239.66" from="694756702#0" to="1461641436" departLane="best" type="veh_passenger" departSpeed="max"/>
    <trip id="veh214" depart="240.79" from="-38359862" to="38393878#1" departLane="best" type="veh_passenger"/>
    <trip id="veh215" depart="241.91" from="-466365026" to="-38393868#2" departLane="best" type="veh_passenger" departSpeed="max"/>
    <trip id="veh216" depart="243.04" from="-424514808" to="-1473695733" departLane="best" type="veh_passenger" departSpeed="max"/>
    <trip id="veh217" depart="244.16" from="-203589976#3" to="38375823#0" departLane="best" type="veh_passenger"/>
    <trip id="veh218" depart="245.29" from="1104045493#1" to="-1004737860" departLane="best" type="veh_passenger"/>
    <trip id="veh219" depart="246.41" from="723312334#8" to="-1461641457#1" departLane="best" type="veh_passenger"/>
    <trip id="veh220" depart="247.54" from="-875074258" to="694603074#0" departLane="best" type="veh_passenger"/>
    <trip id="veh221" depart="248.66" from="266143655#0" to="547154357#1" departLane="best" type="veh_passenger" departSpeed="max"/>
    <trip id="veh222" depart="249.79" from="114615023#0" to="-114532723#0" departLane="best" type="veh_passenger" departSpeed="max"/>
    <trip id="veh223" depart="250.92" from="-417235700" to="-1461641443#1" departLane="best" type="veh_passenger" departSpeed="max"/>
    <trip id="veh224" depart="252.04" from="-115508249" to="114533140#1" departLane="best" type="veh_passenger"/>
    <trip id="veh225" depart="253.17" from="-422195693#1" to="-38359868#2" departLane="best" type="veh_passenger" departSpeed="max"/>
    <trip id="veh226" depart="254.29" from="-114531734#2" to="-38359868#2" departLane="best" type="veh_passenger" departSpeed="max"/>
    <trip id="veh227" depart="255.42" from="875027029#1" to="1057883200#1" departLane="best" type="veh_passenger"/>
    <trip id="veh228" depart="256.54" from="-677624523#1" to="114531734#2" departLane="best" type="veh_passenger" departSpeed="max"/>
    <trip id="veh229" depart="257.67" from="114532723#0" to="114533140#1" departLane="best" type="veh_passenger" departSpeed="max"/>
    <trip id="veh230" depart="258.79" from="694603074#0" to="-115561175#1" departLane="best" type="veh_passenger"/>
    <trip id="veh231" depart="259.92" from="266157747" to="203589956#1" departLane="best" type="veh_passenger" departSpeed="max"/>
    <trip id="veh232" depart="261.04" from="38359845#1" to="38375823#0" departLane="best" type="veh_passenger"/>
    <trip id="veh233" depart="262.17" from="38393868#0" to="-115560987" departLane="best" type="veh_passenger"/>
    <trip id="veh234" depart="263.29" from="-723387976#1" to="148331423" departLane="best" type="veh_passenger" departSpeed="max"/>
    <trip id="veh235" depart="264.42" from="38393868#2" to="-103426225#2" departLane="best" type="veh_passenger"/>
    <trip id="veh236" depart="265.54" from="-875027029#2" to="-266143650#2" departLane="best" type="veh_passenger"/>
    <trip id="veh237" depart="266.67" from="-424514808" to="38359894" departLane="best" type="veh_passenger" departSpeed="max"/>
    <trip id="veh238" depart="267.79" from="1461641422#0" to="875070294" departLane="best" type="veh_passenger" departSpeed="max"/>
    <trip id="veh239" depart="268.92" from="116980609#0" to="-1137637521#0" departLane="best" type="veh_passenger" departSpeed="max"/>
    <trip id="veh240" depart="270.04" from="-115684382" to="38359866#1" departLane="best" type="veh_passenger" departSpeed="max"/>
    <trip id="veh241" depart="271.17" from="-108686053#1" to="417228579#1" departLane="best" type="veh_passenger" departSpeed="max"/>
    <trip id="veh242" depart="272.29" from="723313366#2" to="-38375844#3" departLane="best" type="veh_passenger"/>
    <trip id="veh243" depart="273.42" from="1068837569" to="466365026" departLane="best" type="veh_passenger"/>
    <trip id="veh244" depart="274.54" from="266157747" to="-116457542#2" departLane="best" type="veh_passenger" departSpeed="max"/>
    <trip id="veh245" depart="275.67" from="38393992#1" to="38375844#4" departLane="best" type="veh_passenger"/>
    <trip id="veh246" depart="276.79" from="-547154356#1" to="115684382" departLane="best" type="veh_passenger"/>
    <trip id="veh247" depart="277.92" from="38359857#0" to="875149910#1" departLane="best" type="veh_passenger" departSpeed="max"/>
    <trip id="veh248" depart="279.04" from="108045029#0" to="1462125975" departLane="best" type="veh_passenger" departSpeed="max"/>
    <trip id="veh249" depart="280.17" from="266143646#0" to="723313369#4" departLane="best" type="veh_passenger" departSpeed="max"/>
    <trip id="veh250" depart="281.30" from="-116457542#1" to="-116650845#1" departLane="best" type="veh_passenger"/>
    <trip id="veh251" depart="282.42" from="-723312334#4" to="-266143655#10" departLane="best" type="veh_passenger"/>
    <trip id="veh252" depart="283.55" from="723312334#0" to="-266143646#1" departLane="best" type="veh_passenger"/>
    <trip id="veh253" depart="284.67" from="1004744416#0" to="-824174714" departLane="best" type="veh_passenger"/>
    <trip id="veh254" depart="285.80" from="203589970#3" to="1491183965" departLane="best" type="veh_passenger"/>
    <trip id="veh255" depart="286.92" from="-988510418#0" to="-547154355#0" departLane="best" type="veh_passenger"/>
    <trip id="veh256" depart="288.05" from="203589950#0" to="-115561673#1" departLane="best" type="veh_passenger"/>
    <trip id="veh257" depart="289.17" from="459456562" to="-1420160204" departLane="best" type="veh_passenger"/>
    <trip id="veh258" depart="290.30" from="694756702#0" to="-1068024437#0" departLane="best" type="veh_passenger" departSpeed="max"/>
    <trip id="veh259" depart="291.42" from="-1461641433#0" to="38691390#3" departLane="best" type="veh_passenger"/>
    <trip id="veh260" depart="292.55" from="115560946#0" to="-1461641443#1" departLane="best" type="veh_passenger"/>
    <trip id="veh261" depart="293.67" from="-249079040#2" to="1462125975" departLane="best" type="veh_passenger" departSpeed="max"/>
    <trip id="veh262" depart="294.80" from="115561180#2" to="115561170#1" departLane="best" type="veh_passenger"/>
    <trip id="veh263" depart="295.92" from="38375844#4" to="115561179#1" departLane="best" type="veh_passenger"/>
    <trip id="veh264" depart="297.05" from="459456564#5" to="-114532723#0" departLane="best" type="veh_passenger"/>
    <trip id="veh265" depart="298.17" from="-417228579#2" to="115560897" departLane="best" type="veh_passenger" departSpeed="max"/>
    <trip id="veh266" depart="299.30" from="-1420160204" to="203589956#1" departLane="best" type="veh_passenger"/>
    <trip id="veh267" depart="300.42" from="1491183954#1" to="148331423" departLane="best" type="veh_passenger"/>
    <trip id="veh268" depart="301.55" from="-203589956#1" to="87494509#0" departLane="best" type="veh_passenger" departSpeed="max"/>
    <trip id="veh269" depart="302.67" from="115560904#2" to="115514716#3" departLane="best" type="veh_passenger"/>
    <trip id="veh270" depart="303.80" from="-1461641437" to="-1125937900#1" departLane="best" type="veh_passenger"/>
    <trip id="veh271" depart="304.92" from="-115673859#1" to="-38359862" departLane="best" type="veh_passenger" departSpeed="max"/>
    <trip id="veh272" depart="306.05" from="87494509#2" to="38691414#1" departLane="best" type="veh_passenger"/>
    <trip id="veh273" depart="307.17" from="-115673859#1" to="-1137637521#0" departLane="best" type="veh_passenger" departSpeed="max"/>
    <trip id="veh274" depart="308.30" from="-249079040#2" to="116650845#0" departLane="best" type="veh_passenger" departSpeed="max"/>
    <trip id="veh275" depart="309.42" from="-417235700" to="87494509#2" departLane="best" type="veh_passenger" departSpeed="max"/>
    <trip id="veh276" depart="310.55" from="624091858#1" to="203589970#3" departLane="best" type="veh_passenger"/>
    <trip id="veh277" depart="311.68" from="-1461641387" to="115560897" departLane="best" type="veh_passenger" departSpeed="max"/>
    <trip id="veh278" depart="312.80" from="-624091858#3" to="-203589969#0" departLane="best" type="veh_passenger" departSpeed="max"/>
    <trip id="veh279" depart="313.93" from="-988510417#0" to="114150961#2" departLane="best" type="veh_passenger"/>
    <trip id="veh280" depart="315.05" from="-1491172374" to="1030215635" departLane="best" type="veh_passenger"/>
    <trip id="veh281" depart="316.18" from="-422195701" to="1479274894" departLane="best" type="veh_passenger" departSpeed="max"/>
    <trip id="veh282" depart="317.30" from="-1087007031" to="-547154355#0" departLane="best" type="veh_passenger"/>
    <trip id="veh283" depart="318.43" from="-1491172360#1" to="108686053#1" departLane="best" type="veh_passenger"/>
    <trip id="veh284" depart="319.55" from="723313369#4" to="-114615023#0" departLane="best" type="veh_passenger"/>
    <trip id="veh285" depart="320.68" from="-203589962#1" to="-417235727#2" departLane="best" type="veh_passenger"/>
    <trip id="veh286" depart="321.80" from="-453743055" to="243006968#0" departLane="best" type="veh_passenger" departSpeed="max"/>
    <trip id="veh287" depart="322.93" from="1491183960" to="243007677" departLane="best" type="veh_passenger"/>
    <trip id="veh288" depart="324.05" from="266143646#0" to="115673859#1" departLane="best" type="veh_passenger" departSpeed="max"/>
    <trip id="veh289" depart="325.18" from="154717201#0" to="115560903#4" departLane="best" type="veh_passenger" departSpeed="max"/>
    <trip id="veh290" depart="326.30" from="115561079" to="-114615023#4" departLane="best" type="veh_passenger" departSpeed="max"/>
    <trip id="veh291" depart="327.43" from="87494508#5" to="114533140#1" departLane="best" type="veh_passenger"/>
    <trip id="veh292" depart="328.55" from="417228502#2" to="1462125975" departLane="best" type="veh_passenger"/>
    <trip id="veh293" depart="329.68" from="203589978#0" to="694603073" departLane="best" type="veh_passenger"/>
    <trip id="veh294" depart="330.80" from="113595957#0" to="115561170#0" departLane="best" type="veh_passenger" departSpeed="max"/>
    <trip id="veh295" depart="331.93" from="1491172365#2" to="138652753#1" departLane="best" type="veh_passenger"/>
    <trip id="veh296" depart="333.05" from="-466365026" to="1491183965" departLane="best" type="veh_passenger" departSpeed="max"/>
    <trip id="veh297" depart="334.18" from="-624091858#1" to="-114532723#0" departLane="best" type="veh_passenger"/>
    <trip id="veh298" depart="335.30" from="-1491172374" to="453743055" departLane="best" type="veh_passenger"/>
    <trip id="veh299" depart="336.43" from="38393860#0" to="148331423" departLane="best" type="veh_passenger"/>
    <trip id="veh300" depart="337.55" from="723313369#2" to="266143655#9" departLane="best" type="veh_passenger"/>
    <trip id="veh301" depart="338.68" from="-115684382" to="-1461641443#1" departLane="best" type="veh_passenger" departSpeed="max"/>
    <trip id="veh302" depart="339.80" from="203589970#4" to="547154357#3" departLane="best" type="veh_passenger"/>
    <trip id="veh303" depart="340.93" from="1420160204" to="-38691413" departLane="best" type="veh_passenger"/>
    <trip id="veh304" depart="342.05" from="1491183964" to="114614791" departLane="best" type="veh_passenger" departSpeed="max"/>
    <trip id="veh305" depart="343.18" from="243006566#0" to="115560947#0" departLane="best" type="veh_passenger"/>
    <trip id="veh306" depart="344.31" from="-571179089#1" to="1491183944#3" departLane="best" type="veh_passenger" departSpeed="max"/>
    <trip id="veh307" depart="345.43" from="1461641422#0" to="115673962#1" departLane="best" type="veh_passenger" departSpeed="max"/>
    <trip id="veh308" depart="346.56" from="182017479#1" to="422195701" departLane="best" type="veh_passenger"/>
    <trip id="veh309" depart="347.68" from="115508249" to="931220687#2" departLane="best" type="veh_passenger"/>
    <trip id="veh310" depart="348.81" from="108882988" to="203589950#0" departLane="best" type="veh_passenger" departSpeed="max"/>
    <trip id="veh311" depart="349.93" from="116451461#1" to="1491183944#1" departLane="best" type="veh_passenger"/>
    <trip id="veh312" depart="351.06" from="-1491183944#2" to="-1068024437#0" departLane="best" type="veh_passenger"/>
    <trip id="veh313" depart="352.18" from="-422195701" to="-1420160204" departLane="best" type="veh_passenger" departSpeed="max"/>
    <trip id="veh314" depart="353.31" from="115561670#0" to="-1491183966#0" departLane="best" type="veh_passenger" departSpeed="max"/>
    <trip id="veh315" depart="354.43" from="-103426225#1" to="38393992#3" departLane="best" type="veh_passenger"/>
    <trip id="veh316" depart="355.56" from="266157747" to="-875074258" departLane="best" type="veh_passenger" departSpeed="max"/>
    <trip id="veh317" depart="356.68" from="723313366#2" to="-114532723#0" departLane="best" type="veh_passenger"/>
    <trip id="veh318" depart="357.81" from="466354041#0" to="547154357#3" departLane="best" type="veh_passenger"/>
    <trip id="veh319" depart="358.93" from="-38359857#1" to="422195701" departLane="best" type="veh_passenger"/>
    <trip id="veh320" depart="360.06" from="38393992#1" to="-38393860#0" departLane="best" type="veh_passenger"/>
    <trip id="veh321" depart="361.18" from="1068837568" to="108932067" departLane="best" type="veh_passenger"/>
    <trip id="veh322" depart="362.31" from="-87494509#1" to="-1491183964" departLane="best" type="veh_passenger"/>
    <trip id="veh323" depart="363.43" from="417235733#0" to="114533140#1" departLane="best" type="veh_passenger"/>
    <trip id="veh324" depart="364.56" from="-1461641442#1" to="-115561178#2" departLane="best" type="veh_passenger" departSpeed="max"/>
    <trip id="veh325" depart="365.68" from="115561170#2" to="723313368" departLane="best" type="veh_passenger"/>
    <trip id="veh326" depart="366.81" from="1461641388" to="103426225#4" departLane="best" type="veh_passenger"/>
    <trip id="veh327" depart="367.93" from="1461641422#0" to="-108686053#0" departLane="best" type="veh_passenger" departSpeed="max"/>
    <trip id="veh328" depart="369.06" from="266143655#0" to="-114532723#0" departLane="best" type="veh_passenger" departSpeed="max"/>
    <trip id="veh329" depart="370.18" from="115561082#0" to="-115561669#0" departLane="best" type="veh_passenger" departSpeed="max"/>
    <trip id="veh330" depart="371.31" from="1491183946#2" to="203589973#1" departLane="best" type="veh_passenger"/>
    <trip id="veh331" depart="372.43" from="87494508#1" to="547154357#0" departLane="best" type="veh_passenger"/>
    <trip id="veh332" depart="373.56" from="-424514814#1" to="-1137637521#0" departLane="best" type="veh_passenger" departSpeed="max"/>
    <trip id="veh333" depart="374.69" from="115561161#3" to="-723312334#6" departLane="best" type="veh_passenger"/>
    <trip id="veh334" depart="375.81" from="115561079" to="38393992#1" departLane="best" type="veh_passenger" departSpeed="max"/>
    <trip id="veh335" depart="376.94" from="114615023#3" to="417235700" departLane="best" type="veh_passenger"/>
    <trip id="veh336" depart="378.06" from="1004737860" to="417235700" departLane="best" type="veh_passenger"/>
    <trip id="veh337" depart="379.19" from="-1491172372#0" to="115514116#5" departLane="best" type="veh_passenger"/>
    <trip id="veh338" depart="380.31" from="114532723#0" to="1491172361#1" departLane="best" type="veh_passenger" departSpeed="max"/>
    <trip id="veh339" depart="381.44" from="1461641463" to="1491172359#0" departLane="best" type="veh_passenger"/>
    <trip id="veh340" depart="382.56" from="-422195693#1" to="-114532723#0" departLane="best" type="veh_passenger" departSpeed="max"/>
    <trip id="veh341" depart="383.69" from="1461641436" to="548247853#2" departLane="best" type="veh_passenger"/>
    <trip id="veh342" depart="384.81" from="1491172357#1" to="1033645485" departLane="best" type="veh_passenger"/>
    <trip id="veh343" depart="385.94" from="203589978#4" to="1030215636" departLane="best" type="veh_passenger"/>
    <trip id="veh344" depart="387.06" from="-203589976#0" to="-115561670#0" departLane="best" type="veh_passenger"/>
    <trip id="veh345" depart="388.19" from="113595957#0" to="1461641458#2" departLane="best" type="veh_passenger" departSpeed="max"/>
    <trip id="veh346" depart="389.31" from="113595957#0" to="114614791" departLane="best" type="veh_passenger" departSpeed="max"/>
    <trip id="veh347" depart="390.44" from="-949547103#1" to="-1461641457#0" departLane="best" type="veh_passenger" departSpeed="max"/>
    <trip id="veh348" depart="391.56" from="-1461641461" to="-38393992#2" departLane="best" type="veh_passenger"/>
    <trip id="veh349" depart="392.69" from="-1004744417" to="116457542#2" departLane="best" type="veh_passenger"/>
    <trip id="veh350" depart="393.81" from="-114531734#1" to="723313369#4" departLane="best" type="veh_passenger"/>
    <trip id="veh351" depart="394.94" from="-249079040#2" to="-624091858#1" departLane="best" type="veh_passenger" departSpeed="max"/>
    <trip id="veh352" depart="396.06" from="266143655#0" to="101152389" departLane="best" type="veh_passenger" departSpeed="max"/>
    <trip id="veh353" depart="397.19" from="-459456564#4" to="115561180#2" departLane="best" type="veh_passenger"/>
    <trip id="veh354" depart="398.31" from="115560903#1" to="624091858#3" departLane="best" type="veh_passenger"/>
    <trip id="veh355" depart="399.44" from="-203589956#1" to="1491183944#1" departLane="best" type="veh_passenger" departSpeed="max"/>
    <trip id="veh356" depart="400.56" from="-115514116#5" to="115561673#4" departLane="best" type="veh_passenger" departSpeed="max"/>
    <trip id="veh357" depart="401.69" from="-108932067" to="-545148171#1" departLane="best" type="veh_passenger" departSpeed="max"/>
    <trip id="veh358" depart="402.81" from="-875071472" to="931220687#1" departLane="best" type="veh_passenger"/>
    <trip id="veh359" depart="403.94" from="266143655#10" to="453743055" departLane="best" type="veh_passenger"/>
    <trip id="veh360" depart="405.07" from="-545148171#1" to="116457542#3" departLane="best" type="veh_passenger"/>
    <trip id="veh361" depart="406.19" from="1491183954#1" to="-115560946#2" departLane="best" type="veh_passenger"/>
    <trip id="veh362" depart="407.32" from="911225806#0" to="115561669#1" departLane="best" type="veh_passenger"/>
    <trip id="veh363" depart="408.44" from="38375846#2" to="1491183965" departLane="best" type="veh_passenger"/>
    <trip id="veh364" depart="409.57" from="-571179089#1" to="115561180#0" departLane="best" type="veh_passenger" departSpeed="max"/>
    <trip id="veh365" depart="410.69" from="-1462125975" to="-931220687#2" departLane="best" type="veh_passenger" departSpeed="max"/>
    <trip id="veh366" depart="411.82" from="-1491183966#0" to="1283609633#1" departLane="best" type="veh_passenger"/>
    <trip id="veh367" depart="412.94" from="30951906#1" to="1057883200#1" departLane="best" type="veh_passenger"/>
    <trip id="veh368" depart="414.07" from="38691389#0" to="-266143655#0" departLane="best" type="veh_passenger"/>
    <trip id="veh369" depart="415.19" from="108882988" to="466365026" departLane="best" type="veh_passenger" departSpeed="max"/>
    <trip id="veh370" depart="416.32" from="-1461641464" to="38359850#1" departLane="best" type="veh_passenger"/>
    <trip id="veh371" depart="417.44" from="-38393869#1" to="-1461641443#1" departLane="best" type="veh_passenger"/>
    <trip id="veh372" depart="418.57" from="1420160202" to="-38359862" departLane="best" type="veh_passenger"/>
    <trip id="veh373" depart="419.69" from="911225805#1" to="677624523#1" departLane="best" type="veh_passenger"/>
    <trip id="veh374" depart="420.82" from="875021163" to="1004744417" departLane="best" type="veh_passenger" departSpeed="max"/>
    <trip id="veh375" depart="421.94" from="115561082#0" to="249079040#1" departLane="best" type="veh_passenger" departSpeed="max"/>
    <trip id="veh376" depart="423.07" from="184745185#2" to="115561179#1" departLane="best" type="veh_passenger"/>
    <trip id="veh377" depart="424.19" from="875070294" to="266143651#2" departLane="best" type="veh_passenger"/>
    <trip id="veh378" depart="425.32" from="115561078" to="1491183944#0" departLane="best" type="veh_passenger" departSpeed="max"/>
    <trip id="veh379" depart="426.44" from="-1004737861#2" to="154717203#0" departLane="best" type="veh_passenger"/>
    <trip id="veh380" depart="427.57" from="108882988" to="154717203#0" departLane="best" type="veh_passenger" departSpeed="max"/>
    <trip id="veh381" depart="428.69" from="203589969#0" to="875027030" departLane="best" type="veh_passenger"/>
    <trip id="veh382" depart="429.82" from="-203589956#1" to="1462125975" departLane="best" type="veh_passenger" departSpeed="max"/>
    <trip id="veh383" depart="430.94" from="-249079040#2" to="115684382" departLane="best" type="veh_passenger" departSpeed="max"/>
    <trip id="veh384" depart="432.07" from="-1125927213#2" to="547154357#3" departLane="best" type="veh_passenger"/>
    <trip id="veh385" depart="433.19" from="-38393875#3" to="547154357#3" departLane="best" type="veh_passenger"/>
    <trip id="veh386" depart="434.32" from="-949547103#1" to="148331423" departLane="best" type="veh_passenger" departSpeed="max"/>
    <trip id="veh387" depart="435.44" from="203589970#3" to="-694756702#0" departLane="best" type="veh_passenger"/>
    <trip id="veh388" depart="436.57" from="-116457542#2" to="422195693#1" departLane="best" type="veh_passenger"/>
    <trip id="veh389" depart="437.70" from="-108686053#1" to="-266143655#9" departLane="best" type="veh_passenger" departSpeed="max"/>
    <trip id="veh390" depart="438.82" from="-1461641442#1" to="-348587225#1" departLane="best" type="veh_passenger" departSpeed="max"/>
    <trip id="veh391" depart="439.95" from="1461641443#0" to="630462798#5" departLane="best" type="veh_passenger" departSpeed="max"/>
    <trip id="veh392" depart="441.07" from="-115514116#5" to="1057883200#1" departLane="best" type="veh_passenger" departSpeed="max"/>
    <trip id="veh393" depart="442.20" from="-116650845#0" to="453743055" departLane="best" type="veh_passenger"/>
    <trip id="veh394" depart="443.32" from="-677624523#1" to="-911225805#1" departLane="best" type="veh_passenger" departSpeed="max"/>
    <trip id="veh395" depart="444.45" from="417192344#1" to="249079039#1" departLane="best" type="veh_passenger"/>
    <trip id="veh396" depart="445.57" from="-38691386#2" to="-30951906#1" departLane="best" type="veh_passenger"/>
    <trip id="veh397" depart="446.70" from="115561078" to="-115561670#0" departLane="best" type="veh_passenger" departSpeed="max"/>
    <trip id="veh398" depart="447.82" from="-453743055" to="-1491172357#1" departLane="best" type="veh_passenger" departSpeed="max"/>
    <trip id="veh399" depart="448.95" from="38393875#0" to="115673859#1" departLane="best" type="veh_passenger"/>
    <trip id="veh400" depart="450.07" from="-115514116#5" to="-988510418#0" departLane="best" type="veh_passenger" departSpeed="max"/>
    <trip id="veh401" depart="451.20" from="-115560946#0" to="-949547104" departLane="best" type="veh_passenger"/>
    <trip id="veh402" depart="452.32" from="-824174714" to="-114531734#1" departLane="best" type="veh_passenger"/>
    <trip id="veh403" depart="453.45" from="115561669#0" to="115684382" departLane="best" type="veh_passenger" departSpeed="max"/>
    <trip id="veh404" depart="454.57" from="203589950#0" to="1491183966#1" departLane="best" type="veh_passenger"/>
    <trip id="veh405" depart="455.70" from="185549299" to="170772575" departLane="best" type="veh_passenger" departSpeed="max"/>
    <trip id="veh406" depart="456.82" from="-203589956#1" to="1057883200#1" departLane="best" type="veh_passenger" departSpeed="max"/>
    <trip id="veh407" depart="457.95" from="-1462125975" to="-911225805#1" departLane="best" type="veh_passenger" departSpeed="max"/>
    <trip id="veh408" depart="459.07" from="-116625957#1" to="116457542#1" departLane="best" type="veh_passenger"/>
    <trip id="veh409" depart="460.20" from="-115561168#3" to="99682907#2" departLane="best" type="veh_passenger"/>
    <trip id="veh410" depart="461.32" from="115561168#1" to="103426225#6" departLane="best" type="veh_passenger"/>
    <trip id="veh411" depart="462.45" from="1491183963" to="203589970#4" departLane="best" type="veh_passenger" departSpeed="max"/>
    <trip id="veh412" depart="463.57" from="-114531734#2" to="417235700" departLane="best" type="veh_passenger" departSpeed="max"/>
    <trip id="veh413" depart="464.70" from="115560987" to="-115561168#5" departLane="best" type="veh_passenger" departSpeed="max"/>
    <trip id="veh414" depart="465.82" from="154717201#0" to="-694756702#0" departLane="best" type="veh_passenger" departSpeed="max"/>
    <trip id="veh415" depart="466.95" from="1491183964" to="-115561168#5" departLane="best" type="veh_passenger" departSpeed="max"/>
    <trip id="veh416" depart="468.08" from="-114531734#2" to="453743055" departLane="best" type="veh_passenger" departSpeed="max"/>
    <trip id="veh417" depart="469.20" from="108932696" to="1057883200#1" departLane="best" type="veh_passenger"/>
    <trip id="veh418" depart="470.33" from="-624091858#2" to="-1423673546" departLane="best" type="veh_passenger"/>
    <trip id="veh419" depart="471.45" from="1461641422#0" to="154717203#0" departLane="best" type="veh_passenger" departSpeed="max"/>
    <trip id="veh420" depart="472.58" from="-103426225#1" to="723313369#2" departLane="best" type="veh_passenger"/>
    <trip id="veh421" depart="473.70" from="87494508#3" to="694609277#0" departLane="best" type="veh_passenger"/>
    <trip id="veh422" depart="474.83" from="-1461641387" to="-1491183964" departLane="best" type="veh_passenger" departSpeed="max"/>
    <trip id="veh423" depart="475.95" from="-203589956#1" to="-1461641443#1" departLane="best" type="veh_passenger" departSpeed="max"/>
    <trip id="veh424" depart="477.08" from="1461641443#0" to="-1125937899#1" departLane="best" type="veh_passenger" departSpeed="max"/>
    <trip id="veh425" depart="478.20" from="694603076#0" to="-459456564#2" departLane="best" type="veh_passenger"/>
    <trip id="veh426" depart="479.33" from="-249079040#2" to="-114532723#0" departLane="best" type="veh_passenger" departSpeed="max"/>
    <trip id="veh427" depart="480.45" from="-249079040#2" to="115684382" departLane="best" type="veh_passenger" departSpeed="max"/>
    <trip id="veh428" depart="481.58" from="115561079" to="115560902" departLane="best" type="veh_passenger" departSpeed="max"/>
    <trip id="veh429" depart="482.70" from="-115561179#0" to="-108882988" departLane="best" type="veh_passenger"/>
    <trip id="veh430" depart="483.83" from="-115684382" to="1104045493#1" departLane="best" type="veh_passenger" departSpeed="max"/>
    <trip id="veh431" depart="484.95" from="-115684382" to="-38359857#0" departLane="best" type="veh_passenger" departSpeed="max"/>
    <trip id="veh432" depart="486.08" from="115560987" to="115561670#1" departLane="best" type="veh_passenger" departSpeed="max"/>
    <trip id="veh433" depart="487.20" from="113595957#0" to="1491183950#1" departLane="best" type="veh_passenger" departSpeed="max"/>
    <trip id="veh434" depart="488.33" from="185549299" to="-1461641443#1" departLane="best" type="veh_passenger" departSpeed="max"/>
    <trip id="veh435" depart="489.45" from="-875149910#2" to="694603077#1" departLane="best" type="veh_passenger" departSpeed="max"/>
    <trip id="veh436" depart="490.58" from="38375846#2" to="203589978#4" departLane="best" type="veh_passenger"/>
    <trip id="veh437" depart="491.70" from="-115684382" to="-911225805#1" departLane="best" type="veh_passenger" departSpeed="max"/>
    <trip id="veh438" depart="492.83" from="-1491183966#0" to="1428233169" departLane="best" type="veh_passenger"/>
    <trip id="veh439" depart="493.95" from="1462125970" to="1462125975" departLane="best" type="veh_passenger"/>
    <trip id="veh440" depart="495.08" from="266143655#2" to="266143653" departLane="best" type="veh_passenger"/>
    <trip id="veh441" depart="496.20" from="-624091858#1" to="114614791" departLane="best" type="veh_passenger"/>
    <trip id="veh442" depart="497.33" from="1491183957" to="1461641463" departLane="best" type="veh_passenger"/>
    <trip id="veh443" depart="498.46" from="-249079040#2" to="38359866#2" departLane="best" type="veh_passenger" departSpeed="max"/>
    <trip id="veh444" depart="499.58" from="-203589956#1" to="87494508#1" departLane="best" type="veh_passenger" departSpeed="max"/>
    <trip id="veh445" depart="500.71" from="-1420160203" to="1057883200#1" departLane="best" type="veh_passenger"/>
    <trip id="veh446" depart="501.83" from="417192344#2" to="-1461641458#1" departLane="best" type="veh_passenger"/>
    <trip id="veh447" depart="502.96" from="-453743055" to="-115673962#0" departLane="best" type="veh_passenger" departSpeed="max"/>
    <trip id="veh448" depart="504.08" from="-1099670076#1" to="1057883200#1" departLane="best" type="veh_passenger"/>
    <trip id="veh449" depart="505.21" from="-624091858#2" to="1365389583#0" departLane="best" type="veh_passenger"/>
    <trip id="veh450" depart="506.33" from="114532723#0" to="875149910#1" departLane="best" type="veh_passenger" departSpeed="max"/>
    <trip id="veh451" depart="507.46" from="-1461641442#0" to="185546464#2" departLane="best" type="veh_passenger"/>
    <trip id="veh452" depart="508.58" from="-949547103#1" to="115560919#1" departLane="best" type="veh_passenger" departSpeed="max"/>
    <trip id="veh453" depart="509.71" from="-875149910#2" to="-547154355#0" departLane="best" type="veh_passenger" departSpeed="max"/>
    <trip id="veh454" depart="510.83" from="-115561669#1" to="1057883200#1" departLane="best" type="veh_passenger" departSpeed="max"/>
    <trip id="veh455" depart="511.96" from="114532723#0" to="203589956#1" departLane="best" type="veh_passenger" departSpeed="max"/>
    <trip id="veh456" depart="513.08" from="203589978#0" to="547154357#1" departLane="best" type="veh_passenger"/>
    <trip id="veh457" depart="514.21" from="-723387976#1" to="-266143646#1" departLane="best" type="veh_passenger" departSpeed="max"/>
    <trip id="veh458" depart="515.33" from="-115674753#1" to="1461641433#3" departLane="best" type="veh_passenger"/>
    <trip id="veh459" depart="516.46" from="-624091858#2" to="-875071472" departLane="best" type="veh_passenger"/>
    <trip id="veh460" depart="517.58" from="1137637521#1" to="114150961#4" departLane="best" type="veh_passenger"/>
    <trip id="veh461" depart="518.71" from="-38393865" to="-266143655#0" departLane="best" type="veh_passenger"/>
    <trip id="veh462" depart="519.83" from="114532723#1" to="-115561204#0" departLane="best" type="veh_passenger"/>
    <trip id="veh463" depart="520.96" from="115560987" to="38691389#0" departLane="best" type="veh_passenger" departSpeed="max"/>
    <trip id="veh464" depart="522.08" from="547154355#0" to="-1087007031" departLane="best" type="veh_passenger" departSpeed="max"/>
    <trip id="veh465" depart="523.21" from="1004744419" to="-570104370" departLane="best" type="veh_passenger"/>
    <trip id="veh466" depart="524.33" from="-115508249" to="1491183943#1" departLane="best" type="veh_passenger"/>
    <trip id="veh467" depart="525.46" from="-988510421" to="-38359857#0" departLane="best" type="veh_passenger"/>
    <trip id="veh468" depart="526.58" from="266143655#7" to="-114532723#0" departLane="best" type="veh_passenger"/>
    <trip id="veh469" depart="527.71" from="115684389#2" to="453743056" departLane="best" type="veh_passenger"/>
    <trip id="veh470" depart="528.84" from="-630462798#5" to="547154357#3" departLane="best" type="veh_passenger" departSpeed="max"/>
    <trip id="veh471" depart="529.96" from="-108932067" to="1099670075#0" departLane="best" type="veh_passenger" departSpeed="max"/>
    <trip id="veh472" depart="531.09" from="-115514116#5" to="-266143655#10" departLane="best" type="veh_passenger" departSpeed="max"/>
    <trip id="veh473" depart="532.21" from="1461641434#1" to="249079039#1" departLane="best" type="veh_passenger"/>
    <trip id="veh474" depart="533.34" from="-1004744419" to="-115561168#3" departLane="best" type="veh_passenger"/>
    <trip id="veh475" depart="534.46" from="203589970#2" to="1491183965" departLane="best" type="veh_passenger"/>
    <trip id="veh476" depart="535.59" from="-38393992#2" to="-949547104" departLane="best" type="veh_passenger"/>
    <trip id="veh477" depart="536.71" from="114615023#0" to="417235700" departLane="best" type="veh_passenger" departSpeed="max"/>
    <trip id="veh478" depart="537.84" from="115561078" to="154717203#0" departLane="best" type="veh_passenger" departSpeed="max"/>
    <trip id="veh479" depart="538.96" from="203589973#4" to="243006967#1" departLane="best" type="veh_passenger"/>
    <trip id="veh480" depart="540.09" from="103426225#6" to="-1004737861#2" departLane="best" type="veh_passenger"/>
    <trip id="veh481" depart="541.21" from="108882988" to="-266143650#2" departLane="best" type="veh_passenger" departSpeed="max"/>
    <trip id="veh482" depart="542.34" from="115514716#2" to="-1028732094#1" departLane="best" type="veh_passenger"/>
    <trip id="veh483" depart="543.46" from="-115561179#1" to="-30951906#1" departLane="best" type="veh_passenger" departSpeed="max"/>
    <trip id="veh484" depart="544.59" from="824158743#1" to="115561168#7" departLane="best" type="veh_passenger"/>
    <trip id="veh485" depart="545.71" from="-115561179#1" to="108933164" departLane="best" type="veh_passenger" departSpeed="max"/>
    <trip id="veh486" depart="546.84" from="87494508#0" to="-38393993#0" departLane="best" type="veh_passenger"/>
    <trip id="veh487" depart="547.96" from="87494508#0" to="-547154355#0" departLane="best" type="veh_passenger"/>
    <trip id="veh488" depart="549.09" from="417309446#2" to="1491183954#2" departLane="best" type="veh_passenger"/>
    <trip id="veh489" depart="550.21" from="203589954#1" to="115684382" departLane="best" type="veh_passenger"/>
    <trip id="veh490" depart="551.34" from="182017479#1" to="148331423" departLane="best" type="veh_passenger"/>
    <trip id="veh491" depart="552.46" from="1491172367#0" to="-1461641443#1" departLane="best" type="veh_passenger"/>
    <trip id="veh492" depart="553.59" from="203589970#2" to="-114532723#2" departLane="best" type="veh_passenger"/>
    <trip id="veh493" depart="554.71" from="154717201#0" to="466365026" departLane="best" type="veh_passenger" departSpeed="max"/>
    <trip id="veh494" depart="555.84" from="-571179089#1" to="-1461641443#1" departLane="best" type="veh_passenger" departSpeed="max"/>
    <trip id="veh495" depart="556.96" from="-249079040#2" to="1004744419" departLane="best" type="veh_passenger" departSpeed="max"/>
    <trip id="veh496" depart="558.09" from="266143646#0" to="-694756702#0" departLane="best" type="veh_passenger" departSpeed="max"/>
    <trip id="veh497" depart="559.21" from="203589978#0" to="1462125975" departLane="best" type="veh_passenger"/>
    <trip id="veh498" depart="560.34" from="115561078" to="203589970#4" departLane="best" type="veh_passenger" departSpeed="max"/>
    <trip id="veh499" depart="561.47" from="114532723#0" to="38393868#2" departLane="best" type="veh_passenger" departSpeed="max"/>
    <trip id="veh500" depart="562.59" from="694756702#0" to="-1491183964" departLane="best" type="veh_passenger" departSpeed="max"/>
    <trip id="veh501" depart="563.72" from="1068024437#0" to="115514116#0" departLane="best" type="veh_passenger" departSpeed="max"/>
    <trip id="veh502" depart="564.84" from="-453743055" to="114150961#1" departLane="best" type="veh_passenger" departSpeed="max"/>
    <trip id="veh503" depart="565.97" from="-422195693#1" to="453743055" departLane="best" type="veh_passenger" departSpeed="max"/>
    <trip id="veh504" depart="567.09" from="348587225#1" to="-38359845#0" departLane="best" type="veh_passenger"/>
    <trip id="veh505" depart="568.22" from="-38359845#1" to="1461641435" departLane="best" type="veh_passenger"/>
    <trip id="veh506" depart="569.34" from="1491172365#2" to="-108686154#0" departLane="best" type="veh_passenger"/>
    <trip id="veh507" depart="570.47" from="-1491172358" to="683745965#0" departLane="best" type="veh_passenger"/>
    <trip id="veh508" depart="571.59" from="115560987" to="1491183966#0" departLane="best" type="veh_passenger" departSpeed="max"/>
    <trip id="veh509" depart="572.72" from="-115561669#1" to="-911225805#1" departLane="best" type="veh_passenger" departSpeed="max"/>
    <trip id="veh510" depart="573.84" from="115561082#0" to="115560904#0" departLane="best" type="veh_passenger" departSpeed="max"/>
    <trip id="veh511" depart="574.97" from="1461641449#0" to="-1099670076#1" departLane="best" type="veh_passenger"/>
    <trip id="veh512" depart="576.09" from="725287636#2" to="249079040#1" departLane="best" type="veh_passenger"/>
    <trip id="veh513" depart="577.22" from="243006968#0" to="1491183960" departLane="best" type="veh_passenger"/>
    <trip id="veh514" depart="578.34" from="-203589956#1" to="-624091858#2" departLane="best" type="veh_passenger" departSpeed="max"/>
    <trip id="veh515" depart="579.47" from="1420160202" to="154717203#0" departLane="best" type="veh_passenger"/>
    <trip id="veh516" depart="580.59" from="-1461641460" to="203589950#0" departLane="best" type="veh_passenger"/>
    <trip id="veh517" depart="581.72" from="115561078" to="-911225805#1" departLane="best" type="veh_passenger" departSpeed="max"/>
    <trip id="veh518" depart="582.84" from="115561079" to="1125937899#1" departLane="best" type="veh_passenger" departSpeed="max"/>
    <trip id="veh519" depart="583.97" from="1104045493#1" to="547154357#3" departLane="best" type="veh_passenger"/>
    <trip id="veh520" depart="585.09" from="107202366#0" to="-725287636#2" departLane="best" type="veh_passenger"/>
    <trip id="veh521" depart="586.22" from="114615023#3" to="115561673#1" departLane="best" type="veh_passenger"/>
    <trip id="veh522" depart="587.34" from="-115561179#1" to="1423673547#0" departLane="best" type="veh_passenger" departSpeed="max"/>
    <trip id="veh523" depart="588.47" from="1004744416#0" to="624091858#1" departLane="best" type="veh_passenger"/>
    <trip id="veh524" depart="589.59" from="154717201#0" to="38375826" departLane="best" type="veh_passenger" departSpeed="max"/>
    <trip id="veh525" depart="590.72" from="115561079" to="-1461641433#2" departLane="best" type="veh_passenger" departSpeed="max"/>
    <trip id="veh526" depart="591.85" from="203589978#6" to="154717203#0" departLane="best" type="veh_passenger"/>
    <trip id="veh527" depart="592.97" from="-1462125975" to="-949547104" departLane="best" type="veh_passenger" departSpeed="max"/>
    <trip id="veh528" depart="594.10" from="203589954#2" to="-266143646#1" departLane="best" type="veh_passenger"/>
    <trip id="veh529" depart="595.22" from="99682907#2" to="422195701" departLane="best" type="veh_passenger"/>
    <trip id="veh530" depart="596.35" from="-38691386#8" to="-1461641443#1" departLane="best" type="veh_passenger"/>
    <trip id="veh531" depart="597.47" from="-203589969#1" to="115561669#1" departLane="best" type="veh_passenger"/>
    <trip id="veh532" depart="598.60" from="266143646#0" to="1461641449#0" departLane="best" type="veh_passenger" departSpeed="max"/>
    <trip id="veh533" depart="599.72" from="38393992#3" to="545148171#0" departLane="best" type="veh_passenger"/>
</routes>
